powerplug/__init__.py
powerplug/apps.py
powerplug/config.py
powerplug/tasks.py
powerplug/version.py
powerplug/management/__init__.py
powerplug/management/commands/__init__.py
powerplug/management/commands/pluggable.py
powerplug/urls/__init__.py
powerplug/urls/rest.py
powerplug-0.2.0.dist-info/METADATA
powerplug-0.2.0.dist-info/WHEEL
powerplug-0.2.0.dist-info/entry_points.txt
powerplug-0.2.0.dist-info/top_level.txt
powerplug-0.2.0.dist-info/RECORD
